advance_conv_benchmarks/__init__.py
advance_conv_benchmarks/benchmarks/__init__.py
advance_conv_benchmarks/benchmarks/benchmark.py
advance_conv_benchmarks/benchmarks/enhanced_benchmark.py
advance_conv_benchmarks/layers/__init__.py
advance_conv_benchmarks/layers/deformable.py
advance_conv_benchmarks/layers/depthwise_separable.py
advance_conv_benchmarks/layers/dynamic.py
advance_conv_benchmarks/layers/kernel_warehouse.py
advance_conv_benchmarks/layers/omni_dimensional.py
advance_conv_benchmarks/layers/traditional.py
advance_conv_benchmarks/original_scripts/__init__.py
advance_conv_benchmarks/original_scripts/d_ptflops_exact.py
advance_conv_benchmarks/original_scripts/dcnv1_exact.py
advance_conv_benchmarks/original_scripts/ds_ptflops_exact.py
advance_conv_benchmarks/original_scripts/dskw_exact.py
advance_conv_benchmarks/original_scripts/dsodconv_exact.py
advance_conv_benchmarks/original_scripts/trad_convo_exact.py
advance_conv_benchmarks/original_scripts/trad_ptf_exact.py
advance_conv_benchmarks/utils/__init__.py
advance_conv_benchmarks-0.1.0.dist-info/licenses/LICENSE
advance_conv_benchmarks-0.1.0.dist-info/METADATA
advance_conv_benchmarks-0.1.0.dist-info/WHEEL
advance_conv_benchmarks-0.1.0.dist-info/top_level.txt
advance_conv_benchmarks-0.1.0.dist-info/RECORD
