Metadata-Version: 2.4
Name: advance-conv-benchmarks
Version: 0.1.0
Summary: Research reproducibility suite for exact convolution paper reproductions
Home-page: https://github.com/abhudaysingh/advance-conv-benchmarks
Author: Abhudaya Singh
Author-email: Abhudaya Singh <abhuday2656@gmail.com>
License: MIT License
Project-URL: Homepage, https://github.com/abhudaysingh/advance-conv-benchmarks
Project-URL: Repository, https://github.com/abhudaysingh/advance-conv-benchmarks
Project-URL: Documentation, https://github.com/abhudaysingh/advance-conv-benchmarks
Project-URL: Bug Reports, https://github.com/abhudaysingh/advance-conv-benchmarks/issues
Keywords: pytorch,convolution,research,reproducibility,papers,academic,deep learning,computer vision
Classifier: Development Status :: 4 - Beta
Classifier: Intended Audience :: Science/Research
Classifier: Intended Audience :: Education
Classifier: License :: OSI Approved :: MIT License
Classifier: Operating System :: OS Independent
Classifier: Programming Language :: Python :: 3
Classifier: Programming Language :: Python :: 3.8
Classifier: Programming Language :: Python :: 3.9
Classifier: Programming Language :: Python :: 3.10
Classifier: Programming Language :: Python :: 3.11
Classifier: Topic :: Scientific/Engineering :: Artificial Intelligence
Classifier: Topic :: Scientific/Engineering :: Information Analysis
Classifier: Topic :: Software Development :: Libraries :: Python Modules
Classifier: Topic :: Education
Requires-Python: >=3.8
License-File: LICENSE
Requires-Dist: torch>=1.9.0
Requires-Dist: torchvision>=0.10.0
Requires-Dist: numpy>=1.21.0
Requires-Dist: ptflops>=0.6.6
Requires-Dist: tabulate>=0.8.9
Provides-Extra: dev
Requires-Dist: pytest>=6.0; extra == "dev"
Requires-Dist: black>=21.0; extra == "dev"
Requires-Dist: flake8>=3.9; extra == "dev"
Requires-Dist: isort>=5.9; extra == "dev"
Dynamic: author
Dynamic: home-page
Dynamic: license-file
Dynamic: requires-python
